libsonic/__init__.py
libsonic/connection.py
libsonic/errors.py
libsonic/models.py
py_sonic2-1.0.3.dist-info/licenses/LICENSE
py_sonic2-1.0.3.dist-info/METADATA
py_sonic2-1.0.3.dist-info/WHEEL
py_sonic2-1.0.3.dist-info/top_level.txt
py_sonic2-1.0.3.dist-info/RECORD
