Metadata-Version: 2.4
Name: py-sonic2
Version: 1.0.3
Summary: A Python wrapper library for the Subsonic REST API
Home-page: https://github.com/m00n/py-sonic
Author: Yannick Schäfer
Author-email: Yannick Schäfer <mail@m00n.dev>
License-Expression: GPL-3.0-or-later
Project-URL: Homepage, https://github.com/m00n/py-sonic
Project-URL: Bug Tracker, https://github.com/m00n/py-sonic/issues
Project-URL: Source Code, https://github.com/m00n/py-sonic
Keywords: subsonic,api,music,streaming
Classifier: Development Status :: 4 - Beta
Classifier: Intended Audience :: Developers
Classifier: Intended Audience :: System Administrators
Classifier: Intended Audience :: Information Technology
Classifier: Natural Language :: English
Classifier: Operating System :: OS Independent
Classifier: Programming Language :: Python :: 3
Classifier: Programming Language :: Python :: 3.8
Classifier: Programming Language :: Python :: 3.9
Classifier: Programming Language :: Python :: 3.10
Classifier: Programming Language :: Python :: 3.11
Classifier: Programming Language :: Python :: 3.12
Classifier: Programming Language :: Python :: 3.13
Classifier: Topic :: Software Development :: Libraries :: Python Modules
Classifier: Topic :: Multimedia :: Sound/Audio
Classifier: Topic :: Internet :: WWW/HTTP
Requires-Python: >=3.8
License-File: LICENSE
Requires-Dist: pydantic>=2.0.0
Dynamic: author
Dynamic: home-page
Dynamic: license-file
Dynamic: requires-python
